{
  "clientId": "grind_client",
  "name": "",
  "description": "",
  "rootUrl": "",
  "adminUrl": "",
  "baseUrl": "",
  "surrogateAuthRequired": false,
  "enabled": true,
  "alwaysDisplayInConsole": false,
  "clientAuthenticatorType": "client-secret",
  "secret": "b5fk9Hdmxn7kFgJDao2SFFkfVoypa60g",
  "redirectUris": [
    "http://localhost:808*"
  ],
  "webOrigins": [
    "*"
  ],
  "notBefore": 0,
  "bearerOnly": false,
  "consentRequired": false,
  "standardFlowEnabled": true,
  "implicitFlowEnabled": false,
  "directAccessGrantsEnabled": true,
  "serviceAccountsEnabled": true,
  "publicClient": false,
  "frontchannelLogout": true,
  "protocol": "openid-connect",
  "attributes": {
    "realm_client": "false",
    "oidc.ciba.grant.enabled": "false",
    "client.secret.creation.time": "1754594771",
    "backchannel.logout.session.required": "true",
    "standard.token.exchange.enabled": "false",
    "frontchannel.logout.session.required": "true",
    "post.logout.redirect.uris": "http://localhost:808*",
    "display.on.consent.screen": "false",
    "oauth2.device.authorization.grant.enabled": "false",
    "backchannel.logout.revoke.offline.tokens": "false"
  },
  "authenticationFlowBindingOverrides": {},
  "fullScopeAllowed": true,
  "nodeReRegistrationTimeout": -1,
  "protocolMappers": [
    {
      "name": "authorities",
      "protocol": "openid-connect",
      "protocolMapper": "oidc-usermodel-client-role-mapper",
      "consentRequired": false,
      "config": {
        "usermodel.clientRoleMapping.rolePrefix": "ROLE_",
        "introspection.token.claim": "true",
        "multivalued": "true",
        "userinfo.token.claim": "true",
        "id.token.claim": "true",
        "lightweight.claim": "false",
        "access.token.claim": "true",
        "claim.name": "authorities",
        "jsonType.label": "String",
        "usermodel.clientRoleMapping.clientId": "grind-client"
      }
    }
  ],
  "defaultClientScopes": [
    "web-origins",
    "service_account",
    "acr",
    "roles",
    "profile",
    "basic",
    "email"
  ],
  "optionalClientScopes": [
    "address",
    "phone",
    "organization",
    "offline_access",
    "microprofile-jwt"
  ],
  "access": {
    "view": true,
    "configure": true,
    "manage": true
  }
}